{"bomFormat":"CycloneDX","metadata":{"timestamp":"2024-05-02T14:27:37"},"serialNumber":"urn:uuid:e7ec4807-eddd-4647-9919-ffe1a7f10f8d","version":1,"components":[{"version":"1-r23809-234f1a2efa","type":"application","name":"base-files","licenses":[{"license":{"name":"GPL-2.0"}}]},{"cpe":"cpe:/a:busybox:busybox:1.36.1","licenses":[{"license":{"name":"GPL-2.0"}}],"name":"busybox","type":"application","version":"1.36.1"},{"name":"ca-bundle","version":"20230311","type":"application"},{"type":"application","version":"2.90","name":"dnsmasq","licenses":[{"license":{"name":"GPL-2.0"}}],"cpe":"cpe:/a:thekelleys:dnsmasq:2.90"},{"cpe":"cpe:/a:matt_johnston:dropbear_ssh_server:2022.82","version":"2022.82","type":"application","licenses":[{"license":{"name":"MIT"}}],"name":"dropbear"},{"licenses":[{"license":{"name":"GPL-2.0"}}],"name":"e2fsprogs","version":"1.47.0","type":"application","cpe":"cpe:/a:e2fsprogs_project:e2fsprogs:1.47.0"},{"name":"firewall4","licenses":[{"license":{"name":"ISC"}}],"version":"2023-09-01-598d9fbb","type":"application"},{"version":"2023-02-28-bfe882d5","type":"application","name":"fstools","licenses":[{"license":{"name":"GPL-2.0"}}]},{"version":"2019-11-12-8f7fe925","type":"application","licenses":[{"license":{"name":"GPL-2.0"}}],"name":"fwtool"},{"version":"2022-08-13-4c7b720b","type":"application","name":"getrandom","licenses":[{"license":{"name":"GPL-2.0"}}]},{"cpe":"cpe:/a:gnu:grub2:2.06","name":"grub2","licenses":[{"license":{"name":"GPL-3.0-or-later"}}],"version":"2.06","type":"application"},{"name":"grub2-bios-setup","licenses":[{"license":{"name":"GPL-3.0-or-later"}}],"type":"application","version":"2.06","cpe":"cpe:/a:gnu:grub2:2.06"},{"cpe":"cpe:/a:gnu:grub2:2.06","name":"grub2-efi","licenses":[{"license":{"name":"GPL-3.0-or-later"}}],"type":"application","version":"2.06"},{"licenses":[{"license":{"name":"MIT"}}],"name":"jansson","version":"2.14","type":"library","cpe":"cpe:/a:jansson_project:jansson:2.14"},{"licenses":[{"license":{"name":"ISC"}}],"name":"jshn","type":"application","version":"2023-05-23-75a3b870"},{"name":"jsonfilter","licenses":[{"license":{"name":"ISC"}}],"version":"2024-01-23-594cfa86","type":"application"},{"name":"kernel","licenses":[{"license":{"name":"GPL-2.0"}}],"version":"5.15.150","cpe":"cpe:/o:linux:linux_kernel:5.15.150"},{"name":"kmod-button-hotplug","licenses":[{"license":{"name":"GPL-2.0"}}],"type":"application","version":"5.15.150"},{"licenses":[{"license":{"name":"GPL-2.0"}}],"name":"kmod-crypto-acompress","version":"5.15.150","type":"application"},{"name":"kmod-crypto-crc32c","licenses":[{"license":{"name":"GPL-2.0"}}],"version":"5.15.150","type":"application"},{"licenses":[{"license":{"name":"GPL-2.0"}}],"name":"kmod-crypto-hash","type":"application","version":"5.15.150"},{"licenses":[{"license":{"name":"GPL-2.0"}}],"name":"kmod-fs-vfat","version":"5.15.150","type":"application"},{"licenses":[{"license":{"name":"GPL-2.0"}}],"name":"kmod-input-core","version":"5.15.150","type":"application"},{"name":"kmod-lib-crc-ccitt","licenses":[{"license":{"name":"GPL-2.0"}}],"type":"application","version":"5.15.150"},{"type":"application","version":"5.15.150","name":"kmod-lib-crc32c","licenses":[{"license":{"name":"GPL-2.0"}}]},{"name":"kmod-lib-lzo","licenses":[{"license":{"name":"GPL-2.0"}}],"type":"application","version":"5.15.150"},{"licenses":[{"license":{"name":"GPL-2.0"}}],"name":"kmod-nf-conntrack","version":"5.15.150","type":"application"},{"licenses":[{"license":{"name":"GPL-2.0"}}],"name":"kmod-nf-conntrack6","type":"application","version":"5.15.150"},{"licenses":[{"license":{"name":"GPL-2.0"}}],"name":"kmod-nf-flow","version":"5.15.150","type":"application"},{"type":"application","version":"5.15.150","licenses":[{"license":{"name":"GPL-2.0"}}],"name":"kmod-nf-log"},{"type":"application","version":"5.15.150","licenses":[{"license":{"name":"GPL-2.0"}}],"name":"kmod-nf-log6"},{"type":"application","version":"5.15.150","licenses":[{"license":{"name":"GPL-2.0"}}],"name":"kmod-nf-nat"},{"licenses":[{"license":{"name":"GPL-2.0"}}],"name":"kmod-nf-reject","version":"5.15.150","type":"application"},{"type":"application","version":"5.15.150","licenses":[{"license":{"name":"GPL-2.0"}}],"name":"kmod-nf-reject6"},{"licenses":[{"license":{"name":"GPL-2.0"}}],"name":"kmod-nfnetlink","type":"application","version":"5.15.150"},{"name":"kmod-nft-core","licenses":[{"license":{"name":"GPL-2.0"}}],"type":"application","version":"5.15.150"},{"name":"kmod-nft-fib","licenses":[{"license":{"name":"GPL-2.0"}}],"type":"application","version":"5.15.150"},{"version":"5.15.150","type":"application","name":"kmod-nft-nat","licenses":[{"license":{"name":"GPL-2.0"}}]},{"type":"application","version":"5.15.150","name":"kmod-nft-offload","licenses":[{"license":{"name":"GPL-2.0"}}]},{"name":"kmod-nls-base","licenses":[{"license":{"name":"GPL-2.0"}}],"type":"application","version":"5.15.150"},{"version":"5.15.150","type":"application","licenses":[{"license":{"name":"GPL-2.0"}}],"name":"kmod-nls-cp437"},{"version":"5.15.150","type":"application","name":"kmod-nls-iso8859-1","licenses":[{"license":{"name":"GPL-2.0"}}]},{"licenses":[{"license":{"name":"GPL-2.0"}}],"name":"kmod-nls-utf8","type":"application","version":"5.15.150"},{"name":"kmod-ppp","licenses":[{"license":{"name":"GPL-2.0"}}],"version":"5.15.150","type":"application"},{"name":"kmod-pppoe","licenses":[{"license":{"name":"GPL-2.0"}}],"type":"application","version":"5.15.150"},{"licenses":[{"license":{"name":"GPL-2.0"}}],"name":"kmod-pppox","type":"application","version":"5.15.150"},{"version":"5.15.150","type":"application","licenses":[{"license":{"name":"GPL-2.0"}}],"name":"kmod-slhc"},{"cpe":"cpe:/a:kernel:util-linux:2.39","name":"libblkid","licenses":[{"license":{"name":"GPL-2.0-only"}}],"version":"2.39","type":"library"},{"version":"2023-05-23-75a3b870","type":"library","licenses":[{"license":{"name":"ISC"}}],"name":"libblobmsg-json"},{"name":"libc","licenses":[{"license":{"name":"GPL-3.0-with-GCC-exception"}}],"type":"application","version":"1.2.4"},{"version":"1.47.0","type":"library","licenses":[{"license":{"name":"GPL-2.0"}}],"name":"libcomerr","cpe":"cpe:/a:e2fsprogs_project:e2fsprogs:1.47.0"},{"cpe":"cpe:/a:e2fsprogs_project:e2fsprogs:1.47.0","type":"library","version":"1.47.0","name":"libext2fs","licenses":[{"license":{"name":"GPL-2.0"}}]},{"cpe":"cpe:/a:f2fs-tools_project:f2fs-tools:1.16.0","version":"1.16.0","type":"library","name":"libf2fs","licenses":[{"license":{"name":"GPL-2.0-only"}}]},{"version":"12.3.0","type":"application","name":"libgcc","licenses":[{"license":{"name":"GPL-3.0-with-GCC-exception"}}]},{"cpe":"cpe:/a:json-c_project:json-c:0.16","type":"library","version":"0.16","name":"libjson-c","licenses":[{"license":{"name":"MIT"}}]},{"type":"application","version":"2023-05-23-75a3b870","licenses":[{"license":{"name":"ISC"}}],"name":"libjson-script"},{"cpe":"cpe:/a:arm:mbed_tls:2.28.7","name":"libmbedtls","licenses":[{"license":{"name":"GPL-2.0-or-later"}}],"type":"library","version":"2.28.7"},{"licenses":[{"license":{"name":"LGPL-2.1+"}}],"name":"libmnl","type":"library","version":"1.0.5","cpe":"cpe:/a:netfilter:libmnl:1.0.5"},{"cpe":"cpe:/a:netfilter:libnftnl:1.2.6","licenses":[{"license":{"name":"GPL-2.0-or-later"}}],"name":"libnftnl","version":"1.2.6","type":"library"},{"type":"library","version":"2023-07-27-bc92a280","name":"libnl-tiny","licenses":[{"license":{"name":"LGPL-2.1"}}]},{"name":"libpthread","licenses":[{"license":{"name":"GPL-3.0-with-GCC-exception"}}],"version":"1.2.4","type":"application"},{"version":"1.2.4","type":"application","licenses":[{"license":{"name":"GPL-3.0-with-GCC-exception"}}],"name":"librt"},{"cpe":"cpe:/a:kernel:util-linux:2.39","type":"library","version":"2.39","name":"libsmartcols","licenses":[{"license":{"name":"GPL-2.0-only"}}]},{"cpe":"cpe:/a:e2fsprogs_project:e2fsprogs:1.47.0","name":"libss","licenses":[{"license":{"name":"GPL-2.0"}}],"type":"library","version":"1.47.0"},{"name":"libubox","licenses":[{"license":{"name":"ISC"}}],"version":"2023-05-23-75a3b870","type":"library"},{"version":"2023-06-05-f787c97b","type":"library","licenses":[{"license":{"name":"LGPL-2.1"}}],"name":"libubus"},{"name":"libuci","licenses":[{"license":{"name":"LGPL-2.1"}}],"type":"library","version":"2023-08-10-5781664d"},{"version":"2023-04-13-007d9454","type":"library","licenses":[{"license":{"name":"ISC"}}],"name":"libuclient"},{"licenses":[{"license":{"name":"ISC"}}],"name":"libucode","type":"library","version":"2023-11-07-a6e75e02"},{"version":"2023-02-25-498f6e26","type":"library","name":"libustream-mbedtls","licenses":[{"license":{"name":"ISC"}}]},{"version":"2.39","type":"library","name":"libuuid","licenses":[{"license":{"name":"GPL-2.0-only"}}],"cpe":"cpe:/a:kernel:util-linux:2.39"},{"version":"2022-08-13-4c7b720b","type":"application","licenses":[{"license":{"name":"GPL-2.0"}}],"name":"logd"},{"licenses":[{"license":{"name":"GPL-2.0-only"}}],"name":"mkf2fs","version":"1.16.0","type":"application","cpe":"cpe:/a:f2fs-tools_project:f2fs-tools:1.16.0"},{"name":"mtd","licenses":[{"license":{"name":"GPL-2.0+"}}],"version":"26","type":"application"},{"version":"2024-01-04-c18cc79d","type":"application","name":"netifd","licenses":[{"license":{"name":"GPL-2.0"}}]},{"version":"1.0.8","type":"application","name":"nftables-json","licenses":[{"license":{"name":"GPL-2.0"}}]},{"name":"odhcp6c","licenses":[{"license":{"name":"GPL-2.0"}}],"type":"application","version":"2023-05-12-bcd28363"},{"licenses":[{"license":{"name":"GPL-2.0"}}],"name":"odhcpd-ipv6only","type":"application","version":"2023-10-24-d8118f6e"},{"licenses":[{"license":{"name":"GPL-2.0"}}],"name":"openwrt-keyring","version":"2022-03-25-62471e69","type":"application"},{"name":"opkg","licenses":[{"license":{"name":"GPL-2.0"}}],"type":"application","version":"2022-02-24-d038e5b6"},{"cpe":"cpe:/a:kernel:util-linux:2.39","version":"2.39","type":"application","licenses":[{"license":{"name":"GPL-2.0-only"}}],"name":"partx-utils"},{"cpe":"cpe:/a:samba:ppp:2.4.9.git-2021-01-04","type":"application","version":"2.4.9.git-2021-01-04","name":"ppp","licenses":[{"license":{"name":"BSD-4-Clause"}}]},{"cpe":"cpe:/a:samba:ppp:2.4.9.git-2021-01-04","version":"2.4.9.git-2021-01-04","type":"application","licenses":[{"license":{"name":"BSD-4-Clause"}}],"name":"ppp-mod-pppoe"},{"version":"2023-06-25-2db83655","type":"application","licenses":[{"license":{"name":"GPL-2.0"}}],"name":"procd"},{"type":"application","version":"2023-06-25-2db83655","licenses":[{"license":{"name":"GPL-2.0"}}],"name":"procd-seccomp"},{"name":"procd-ujail","licenses":[{"license":{"name":"GPL-2.0"}}],"version":"2023-06-25-2db83655","type":"application"},{"licenses":[{"license":{"name":"GPL-2.0"}}],"name":"ubox","version":"2022-08-13-4c7b720b","type":"application"},{"type":"application","version":"2023-06-05-f787c97b","name":"ubus","licenses":[{"license":{"name":"LGPL-2.1"}}]},{"type":"application","version":"2023-06-05-f787c97b","name":"ubusd","licenses":[{"license":{"name":"LGPL-2.1"}}]},{"name":"uci","licenses":[{"license":{"name":"LGPL-2.1"}}],"type":"application","version":"2023-08-10-5781664d"},{"licenses":[{"license":{"name":"ISC"}}],"name":"uclient-fetch","version":"2023-04-13-007d9454","type":"application"},{"name":"ucode","licenses":[{"license":{"name":"ISC"}}],"type":"application","version":"2023-11-07-a6e75e02"},{"name":"ucode-mod-fs","licenses":[{"license":{"name":"ISC"}}],"version":"2023-11-07-a6e75e02","type":"application"},{"type":"application","version":"2023-11-07-a6e75e02","name":"ucode-mod-ubus","licenses":[{"license":{"name":"ISC"}}]},{"licenses":[{"license":{"name":"ISC"}}],"name":"ucode-mod-uci","type":"application","version":"2023-11-07-a6e75e02"},{"type":"application","version":"3","licenses":[{"license":{"name":"GPL-2.0-only"}}],"name":"urandom-seed"},{"name":"urngd","licenses":[{"license":{"name":"GPL-2.0"}},{"license":{"name":"BSD-3-Clause"}}],"version":"2023-11-01-44365eb1","type":"application"},{"type":"application","version":"2020-05-23-f1f65026","licenses":[{"license":{"name":"ISC"}}],"name":"usign"}],"specVersion":"1.4"}